etherstan/__init__.py
etherstan/__version__.py
etherstan/cli.py
etherstan/get.py
etherstan-0.0.0.dist-info/LICENSE
etherstan-0.0.0.dist-info/METADATA
etherstan-0.0.0.dist-info/WHEEL
etherstan-0.0.0.dist-info/entry_points.txt
etherstan-0.0.0.dist-info/top_level.txt
etherstan-0.0.0.dist-info/zip-safe
etherstan-0.0.0.dist-info/RECORD
