Metadata-Version: 2.1
Name: etherstan
Version: 0.0.0
Summary: A tool for extracting Ethereum addresses from comment threads on Reddit and Twitter
Home-page: https://gitlab.com/GoodLuckHF/etherstan
Author: The Yellow Dart
License: GNU Affero General Public License v3
Keywords: NFT,cryptocurrency,Ethereum,Etherscan,webscraping
Classifier: Programming Language :: Python
Classifier: Programming Language :: Python :: 3
Classifier: Programming Language :: Python :: 3.10
Classifier: License :: OSI Approved :: GNU Affero General Public License v3
Classifier: Operating System :: Microsoft :: Windows
Classifier: Operating System :: Unix
Classifier: Operating System :: MacOS
Classifier: Topic :: Utilities
Requires-Python: >=3.10
License-File: LICENSE
Requires-Dist: numpy
Requires-Dist: pandas
Requires-Dist: etherscan-python
